COIM/__init__.py
COIM/constrain.py
COIM/constrain_add_scalar.py
COIM/constrain_constant_sum.py
COIM/constrain_custom.py
COIM/constrain_mul_scalar.py
COIM/operator.py
COIM-0.0.2.dist-info/LICENSE
COIM-0.0.2.dist-info/METADATA
COIM-0.0.2.dist-info/WHEEL
COIM-0.0.2.dist-info/top_level.txt
COIM-0.0.2.dist-info/RECORD
