Metadata-Version: 2.1
Name: COIM
Version: 0.0.2
Summary: Constrain Operator for Inferential Models is a simple tool for pre and pos processing of data to eliminate redunduncy in datasets caused by dependency rules between the variables/columns.
Author-email: Miguel Sarraf <miguel.sarraf@alumni.usp.br>
Project-URL: Homepage, https://github.com/MiguelSarraf/COIM
Project-URL: Issues, https://github.com/MiguelSarraf/COIM/issues
Classifier: Development Status :: 4 - Beta
Classifier: Programming Language :: Python :: 3
Classifier: License :: OSI Approved :: MIT License
Classifier: Operating System :: OS Independent
Classifier: Intended Audience :: Developers
Classifier: Intended Audience :: Information Technology
Classifier: Intended Audience :: Science/Research
Classifier: Natural Language :: English
Classifier: Topic :: Database
Classifier: Topic :: Scientific/Engineering
Classifier: Topic :: Software Development
Classifier: Topic :: Software Development :: Pre-processors
Requires-Python: >=3.8
License-File: LICENSE
Requires-Dist: pandas >=1.1.5
Requires-Dist: numpy >=1.19.3
Requires-Dist: prettytable >=2.5.0
